{
  "timestamp_iso": "2026-04-19T14:21:08",
  "unix_time": 1776622868.8260257,
  "temperature_c": 22.9,
  "humidity_rh": 56.6,
  "recognized_digits": {
    "T1": "2",
    "T2": "2",
    "T3": "9",
    "H1": "5",
    "H2": "6",
    "H3": "6"
  },
  "digit_results": {
    "T1": {
      "digit": "2",
      "score": 25798435.0,
      "confidence": null,
      "engine_used": "template_after_low_keras_confidence",
      "keras_confidence": 0.11375299096107483
    },
    "T2": {
      "digit": "2",
      "score": 22084033.0,
      "confidence": null,
      "engine_used": "template_after_low_keras_confidence",
      "keras_confidence": 0.11941685527563095
    },
    "T3": {
      "digit": "9",
      "score": 15032659.0,
      "confidence": null,
      "engine_used": "template_after_low_keras_confidence",
      "keras_confidence": 0.24881483614444733
    },
    "H1": {
      "digit": "5",
      "score": 19091148.0,
      "confidence": null,
      "engine_used": "template_after_low_keras_confidence",
      "keras_confidence": 0.1548813432455063
    },
    "H2": {
      "digit": "6",
      "score": 13774118.0,
      "confidence": null,
      "engine_used": "template_after_low_keras_confidence",
      "keras_confidence": 0.21659214794635773
    },
    "H3": {
      "digit": "6",
      "score": 13473451.0,
      "confidence": null,
      "engine_used": "template_after_low_keras_confidence",
      "keras_confidence": 0.22905132174491882
    }
  },
  "scores": {
    "T1": 25798435.0,
    "T2": 22084033.0,
    "T3": 15032659.0,
    "H1": 19091148.0,
    "H2": 13774118.0,
    "H3": 13473451.0
  },
  "engine_requested": "keras_then_template",
  "engine_used": "template_after_low_keras_confidence",
  "keras_confidence": null,
  "rotation": "180",
  "rotation_degrees": -7.0,
  "main_crop": {
    "x": 290,
    "y": 370,
    "w": 200,
    "h": 300
  },
  "digit_box_size": {
    "w": 450,
    "h": 800
  }
}