{
  "timestamp_iso": "2026-04-20T09:30:15",
  "unix_time": 1776691815.036953,
  "temperature_c": 62.0,
  "humidity_rh": 56.2,
  "recognized_digits": {
    "T1": "6",
    "T2": "2",
    "T3": "0",
    "H1": "5",
    "H2": "6",
    "H3": "2"
  },
  "digit_results": {
    "T1": {
      "digit": "6",
      "score": 26360023.0,
      "confidence": null,
      "engine_used": "template_after_low_keras_confidence",
      "keras_confidence": 0.11350325495004654
    },
    "T2": {
      "digit": "2",
      "score": 24740191.0,
      "confidence": null,
      "engine_used": "template_after_low_keras_confidence",
      "keras_confidence": 0.11166217178106308
    },
    "T3": {
      "digit": "0",
      "score": 17112051.0,
      "confidence": null,
      "engine_used": "template_after_low_keras_confidence",
      "keras_confidence": 0.2034343034029007
    },
    "H1": {
      "digit": "5",
      "score": 21332879.0,
      "confidence": null,
      "engine_used": "template_after_low_keras_confidence",
      "keras_confidence": 0.14711497724056244
    },
    "H2": {
      "digit": "6",
      "score": 11891149.0,
      "confidence": null,
      "engine_used": "template_after_low_keras_confidence",
      "keras_confidence": 0.21859458088874817
    },
    "H3": {
      "digit": "2",
      "score": 16778307.0,
      "confidence": null,
      "engine_used": "template_after_low_keras_confidence",
      "keras_confidence": 0.19517795741558075
    }
  },
  "scores": {
    "T1": 26360023.0,
    "T2": 24740191.0,
    "T3": 17112051.0,
    "H1": 21332879.0,
    "H2": 11891149.0,
    "H3": 16778307.0
  },
  "engine_requested": "keras_then_template",
  "engine_used": "template_after_low_keras_confidence",
  "keras_confidence": null,
  "rotation": "180",
  "rotation_degrees": -7.0,
  "main_crop": {
    "x": 290,
    "y": 370,
    "w": 200,
    "h": 300
  },
  "digit_box_size": {
    "w": 450,
    "h": 800
  }
}