{
  "timestamp_iso": "2026-04-22T22:57:49",
  "unix_time": 1776913069.2540727,
  "temperature_c": 62.0,
  "humidity_rh": 6.6,
  "recognized_digits": {
    "T1": "6",
    "T2": "2",
    "T3": "0",
    "H1": "0",
    "H2": "6",
    "H3": "6"
  },
  "digit_results": {
    "T1": {
      "digit": "6",
      "score": 25972760.0,
      "confidence": null,
      "engine_used": "template_after_low_keras_confidence",
      "keras_confidence": 0.1138334572315216
    },
    "T2": {
      "digit": "2",
      "score": 25028450.0,
      "confidence": null,
      "engine_used": "template_after_low_keras_confidence",
      "keras_confidence": 0.11277499049901962
    },
    "T3": {
      "digit": "0",
      "score": 16739472.0,
      "confidence": null,
      "engine_used": "template_after_low_keras_confidence",
      "keras_confidence": 0.21029609441757202
    },
    "H1": {
      "digit": "0",
      "score": 20996531.0,
      "confidence": null,
      "engine_used": "template_after_low_keras_confidence",
      "keras_confidence": 0.14442357420921326
    },
    "H2": {
      "digit": "6",
      "score": 12661249.0,
      "confidence": null,
      "engine_used": "template_after_low_keras_confidence",
      "keras_confidence": 0.22351521253585815
    },
    "H3": {
      "digit": "6",
      "score": 14106325.0,
      "confidence": null,
      "engine_used": "template_after_low_keras_confidence",
      "keras_confidence": 0.24200989305973053
    }
  },
  "scores": {
    "T1": 25972760.0,
    "T2": 25028450.0,
    "T3": 16739472.0,
    "H1": 20996531.0,
    "H2": 12661249.0,
    "H3": 14106325.0
  },
  "engine_requested": "keras_then_template",
  "engine_used": "template_after_low_keras_confidence",
  "keras_confidence": null,
  "rotation": "180",
  "rotation_degrees": -7.0,
  "main_crop": {
    "x": 290,
    "y": 370,
    "w": 200,
    "h": 300
  },
  "digit_box_size": {
    "w": 450,
    "h": 800
  }
}