{
  "timestamp_iso": "2026-04-27T12:26:44",
  "unix_time": 1777307204.0349998,
  "temperature_c": 66.0,
  "humidity_rh": 66.6,
  "recognized_digits": {
    "T1": "6",
    "T2": "6",
    "T3": "0",
    "H1": "6",
    "H2": "6",
    "H3": "6"
  },
  "digit_results": {
    "T1": {
      "digit": "6",
      "score": 26445394.0,
      "confidence": null,
      "engine_used": "template_after_low_keras_confidence",
      "keras_confidence": 0.11363733559846878
    },
    "T2": {
      "digit": "6",
      "score": 25899696.0,
      "confidence": null,
      "engine_used": "template_after_low_keras_confidence",
      "keras_confidence": 0.11366941034793854
    },
    "T3": {
      "digit": "0",
      "score": 20724637.0,
      "confidence": null,
      "engine_used": "template_after_low_keras_confidence",
      "keras_confidence": 0.1451677531003952
    },
    "H1": {
      "digit": "6",
      "score": 23060989.0,
      "confidence": null,
      "engine_used": "template_after_low_keras_confidence",
      "keras_confidence": 0.13618025183677673
    },
    "H2": {
      "digit": "6",
      "score": 13620391.0,
      "confidence": null,
      "engine_used": "template_after_low_keras_confidence",
      "keras_confidence": 0.19275353848934174
    },
    "H3": {
      "digit": "6",
      "score": 12352928.0,
      "confidence": null,
      "engine_used": "template_after_low_keras_confidence",
      "keras_confidence": 0.16257990896701813
    }
  },
  "scores": {
    "T1": 26445394.0,
    "T2": 25899696.0,
    "T3": 20724637.0,
    "H1": 23060989.0,
    "H2": 13620391.0,
    "H3": 12352928.0
  },
  "engine_requested": "keras_then_template",
  "engine_used": "template_after_low_keras_confidence",
  "keras_confidence": null,
  "rotation": "180",
  "rotation_degrees": -7.0,
  "main_crop": {
    "x": 290,
    "y": 370,
    "w": 200,
    "h": 300
  },
  "digit_box_size": {
    "w": 450,
    "h": 800
  }
}