{
  "timestamp_iso": "2026-04-20T04:40:20",
  "unix_time": 1776674420.9716856,
  "temperature_c": 60.0,
  "humidity_rh": 56.6,
  "recognized_digits": {
    "T1": "6",
    "T2": "0",
    "T3": "0",
    "H1": "5",
    "H2": "6",
    "H3": "6"
  },
  "digit_results": {
    "T1": {
      "digit": "6",
      "score": 26151568.0,
      "confidence": null,
      "engine_used": "template_after_low_keras_confidence",
      "keras_confidence": 0.11340343207120895
    },
    "T2": {
      "digit": "0",
      "score": 22854004.0,
      "confidence": null,
      "engine_used": "template_after_low_keras_confidence",
      "keras_confidence": 0.11491719633340836
    },
    "T3": {
      "digit": "0",
      "score": 16163552.0,
      "confidence": null,
      "engine_used": "template_after_low_keras_confidence",
      "keras_confidence": 0.22630366683006287
    },
    "H1": {
      "digit": "5",
      "score": 19831764.0,
      "confidence": null,
      "engine_used": "template_after_low_keras_confidence",
      "keras_confidence": 0.14956890046596527
    },
    "H2": {
      "digit": "6",
      "score": 13009333.0,
      "confidence": null,
      "engine_used": "template_after_low_keras_confidence",
      "keras_confidence": 0.21571926772594452
    },
    "H3": {
      "digit": "6",
      "score": 15217541.0,
      "confidence": null,
      "engine_used": "template_after_low_keras_confidence",
      "keras_confidence": 0.24013282358646393
    }
  },
  "scores": {
    "T1": 26151568.0,
    "T2": 22854004.0,
    "T3": 16163552.0,
    "H1": 19831764.0,
    "H2": 13009333.0,
    "H3": 15217541.0
  },
  "engine_requested": "keras_then_template",
  "engine_used": "template_after_low_keras_confidence",
  "keras_confidence": null,
  "rotation": "180",
  "rotation_degrees": -7.0,
  "main_crop": {
    "x": 290,
    "y": 370,
    "w": 200,
    "h": 300
  },
  "digit_box_size": {
    "w": 450,
    "h": 800
  }
}