{
  "timestamp_iso": "2026-04-29T04:42:12",
  "unix_time": 1777452132.3907657,
  "temperature_c": 22.1,
  "humidity_rh": 16.6,
  "recognized_digits": {
    "T1": "2",
    "T2": "2",
    "T3": "1",
    "H1": "1",
    "H2": "6",
    "H3": "6"
  },
  "digit_results": {
    "T1": {
      "digit": "2",
      "score": 12067355.0,
      "confidence": null,
      "engine_used": "template_after_low_keras_confidence",
      "keras_confidence": 0.18207593262195587
    },
    "T2": {
      "digit": "2",
      "score": 10612957.0,
      "confidence": null,
      "engine_used": "template_after_low_keras_confidence",
      "keras_confidence": 0.19852003455162048
    },
    "T3": {
      "digit": "1",
      "score": 11844663.0,
      "confidence": null,
      "engine_used": "template_after_low_keras_confidence",
      "keras_confidence": 0.15287251770496368
    },
    "H1": {
      "digit": "1",
      "score": 12270295.0,
      "confidence": null,
      "engine_used": "template_after_low_keras_confidence",
      "keras_confidence": 0.14822271466255188
    },
    "H2": {
      "digit": "6",
      "score": 12597344.0,
      "confidence": null,
      "engine_used": "template_after_low_keras_confidence",
      "keras_confidence": 0.18074050545692444
    },
    "H3": {
      "digit": "6",
      "score": 13752451.0,
      "confidence": null,
      "engine_used": "template_after_low_keras_confidence",
      "keras_confidence": 0.19851405918598175
    }
  },
  "scores": {
    "T1": 12067355.0,
    "T2": 10612957.0,
    "T3": 11844663.0,
    "H1": 12270295.0,
    "H2": 12597344.0,
    "H3": 13752451.0
  },
  "engine_requested": "keras_then_template",
  "engine_used": "template_after_low_keras_confidence",
  "keras_confidence": null,
  "rotation": "180",
  "rotation_degrees": -7.0,
  "main_crop": {
    "x": 290,
    "y": 370,
    "w": 200,
    "h": 300
  },
  "digit_box_size": {
    "w": 450,
    "h": 800
  }
}