{
  "timestamp_iso": "2026-04-17T22:44:06",
  "unix_time": 1776480246.0736845,
  "temperature_c": 22.0,
  "humidity_rh": 56.5,
  "recognized_digits": {
    "T1": "2",
    "T2": "2",
    "T3": "0",
    "H1": "5",
    "H2": "6",
    "H3": "5"
  },
  "digit_results": {
    "T1": {
      "digit": "2",
      "score": 25879485.0,
      "confidence": null,
      "engine_used": "template_after_low_keras_confidence",
      "keras_confidence": 0.11393413692712784
    },
    "T2": {
      "digit": "2",
      "score": 21808441.0,
      "confidence": null,
      "engine_used": "template_after_low_keras_confidence",
      "keras_confidence": 0.11896944791078568
    },
    "T3": {
      "digit": "0",
      "score": 14794939.0,
      "confidence": null,
      "engine_used": "template_after_low_keras_confidence",
      "keras_confidence": 0.23591306805610657
    },
    "H1": {
      "digit": "5",
      "score": 19658011.0,
      "confidence": null,
      "engine_used": "template_after_low_keras_confidence",
      "keras_confidence": 0.16671942174434662
    },
    "H2": {
      "digit": "6",
      "score": 11969317.0,
      "confidence": null,
      "engine_used": "template_after_low_keras_confidence",
      "keras_confidence": 0.21589471399784088
    },
    "H3": {
      "digit": "5",
      "score": 12576874.0,
      "confidence": null,
      "engine_used": "template_after_low_keras_confidence",
      "keras_confidence": 0.19280461966991425
    }
  },
  "scores": {
    "T1": 25879485.0,
    "T2": 21808441.0,
    "T3": 14794939.0,
    "H1": 19658011.0,
    "H2": 11969317.0,
    "H3": 12576874.0
  },
  "engine_requested": "keras_then_template",
  "engine_used": "template_after_low_keras_confidence",
  "keras_confidence": null,
  "rotation": "180",
  "rotation_degrees": -7.0,
  "main_crop": {
    "x": 290,
    "y": 370,
    "w": 200,
    "h": 300
  },
  "digit_box_size": {
    "w": 450,
    "h": 800
  }
}