{
  "timestamp_iso": "2026-04-18T08:38:01",
  "unix_time": 1776515881.2948062,
  "temperature_c": 62.0,
  "humidity_rh": 51.2,
  "recognized_digits": {
    "T1": "6",
    "T2": "2",
    "T3": "0",
    "H1": "5",
    "H2": "1",
    "H3": "2"
  },
  "digit_results": {
    "T1": {
      "digit": "6",
      "score": 25963850.0,
      "confidence": null,
      "engine_used": "template_after_low_keras_confidence",
      "keras_confidence": 0.11371786892414093
    },
    "T2": {
      "digit": "2",
      "score": 22095664.0,
      "confidence": null,
      "engine_used": "template_after_low_keras_confidence",
      "keras_confidence": 0.12822690606117249
    },
    "T3": {
      "digit": "0",
      "score": 15362302.0,
      "confidence": null,
      "engine_used": "template_after_low_keras_confidence",
      "keras_confidence": 0.22478125989437103
    },
    "H1": {
      "digit": "5",
      "score": 17779715.0,
      "confidence": null,
      "engine_used": "template_after_low_keras_confidence",
      "keras_confidence": 0.2176537662744522
    },
    "H2": {
      "digit": "1",
      "score": 12223605.0,
      "confidence": null,
      "engine_used": "template_after_low_keras_confidence",
      "keras_confidence": 0.16684898734092712
    },
    "H3": {
      "digit": "2",
      "score": 13465779.0,
      "confidence": null,
      "engine_used": "template_after_low_keras_confidence",
      "keras_confidence": 0.18994252383708954
    }
  },
  "scores": {
    "T1": 25963850.0,
    "T2": 22095664.0,
    "T3": 15362302.0,
    "H1": 17779715.0,
    "H2": 12223605.0,
    "H3": 13465779.0
  },
  "engine_requested": "keras_then_template",
  "engine_used": "template_after_low_keras_confidence",
  "keras_confidence": null,
  "rotation": "180",
  "rotation_degrees": -7.0,
  "main_crop": {
    "x": 290,
    "y": 370,
    "w": 200,
    "h": 300
  },
  "digit_box_size": {
    "w": 450,
    "h": 800
  }
}