{
  "timestamp_iso": "2026-04-19T06:38:37",
  "unix_time": 1776595117.4584045,
  "temperature_c": 62.0,
  "humidity_rh": 56.6,
  "recognized_digits": {
    "T1": "6",
    "T2": "2",
    "T3": "0",
    "H1": "5",
    "H2": "6",
    "H3": "6"
  },
  "digit_results": {
    "T1": {
      "digit": "6",
      "score": 26259426.0,
      "confidence": null,
      "engine_used": "template_after_low_keras_confidence",
      "keras_confidence": 0.11306106299161911
    },
    "T2": {
      "digit": "2",
      "score": 23904196.0,
      "confidence": null,
      "engine_used": "template_after_low_keras_confidence",
      "keras_confidence": 0.11127592623233795
    },
    "T3": {
      "digit": "0",
      "score": 16634228.0,
      "confidence": null,
      "engine_used": "template_after_low_keras_confidence",
      "keras_confidence": 0.21694160997867584
    },
    "H1": {
      "digit": "5",
      "score": 21422386.0,
      "confidence": null,
      "engine_used": "template_after_low_keras_confidence",
      "keras_confidence": 0.1465979963541031
    },
    "H2": {
      "digit": "6",
      "score": 11519251.0,
      "confidence": null,
      "engine_used": "template_after_low_keras_confidence",
      "keras_confidence": 0.20598924160003662
    },
    "H3": {
      "digit": "6",
      "score": 13281976.0,
      "confidence": null,
      "engine_used": "template_after_low_keras_confidence",
      "keras_confidence": 0.21627019345760345
    }
  },
  "scores": {
    "T1": 26259426.0,
    "T2": 23904196.0,
    "T3": 16634228.0,
    "H1": 21422386.0,
    "H2": 11519251.0,
    "H3": 13281976.0
  },
  "engine_requested": "keras_then_template",
  "engine_used": "template_after_low_keras_confidence",
  "keras_confidence": null,
  "rotation": "180",
  "rotation_degrees": -7.0,
  "main_crop": {
    "x": 290,
    "y": 370,
    "w": 200,
    "h": 300
  },
  "digit_box_size": {
    "w": 450,
    "h": 800
  }
}