{
  "timestamp_iso": "2026-04-17T23:50:04",
  "unix_time": 1776484204.4148045,
  "temperature_c": 62.0,
  "humidity_rh": 56.2,
  "recognized_digits": {
    "T1": "6",
    "T2": "2",
    "T3": "0",
    "H1": "5",
    "H2": "6",
    "H3": "2"
  },
  "digit_results": {
    "T1": {
      "digit": "6",
      "score": 25783195.0,
      "confidence": null,
      "engine_used": "template_after_low_keras_confidence",
      "keras_confidence": 0.11400457471609116
    },
    "T2": {
      "digit": "2",
      "score": 21692729.0,
      "confidence": null,
      "engine_used": "template_after_low_keras_confidence",
      "keras_confidence": 0.12680719792842865
    },
    "T3": {
      "digit": "0",
      "score": 14881758.0,
      "confidence": null,
      "engine_used": "template_after_low_keras_confidence",
      "keras_confidence": 0.22183769941329956
    },
    "H1": {
      "digit": "5",
      "score": 19660681.0,
      "confidence": null,
      "engine_used": "template_after_low_keras_confidence",
      "keras_confidence": 0.17040131986141205
    },
    "H2": {
      "digit": "6",
      "score": 12182237.0,
      "confidence": null,
      "engine_used": "template_after_low_keras_confidence",
      "keras_confidence": 0.22717958688735962
    },
    "H3": {
      "digit": "2",
      "score": 13689092.0,
      "confidence": null,
      "engine_used": "template_after_low_keras_confidence",
      "keras_confidence": 0.1943286806344986
    }
  },
  "scores": {
    "T1": 25783195.0,
    "T2": 21692729.0,
    "T3": 14881758.0,
    "H1": 19660681.0,
    "H2": 12182237.0,
    "H3": 13689092.0
  },
  "engine_requested": "keras_then_template",
  "engine_used": "template_after_low_keras_confidence",
  "keras_confidence": null,
  "rotation": "180",
  "rotation_degrees": -7.0,
  "main_crop": {
    "x": 290,
    "y": 370,
    "w": 200,
    "h": 300
  },
  "digit_box_size": {
    "w": 450,
    "h": 800
  }
}