{
  "timestamp_iso": "2026-04-18T14:33:32",
  "unix_time": 1776537212.4590487,
  "temperature_c": 62.0,
  "humidity_rh": 56.2,
  "recognized_digits": {
    "T1": "6",
    "T2": "2",
    "T3": "0",
    "H1": "5",
    "H2": "6",
    "H3": "2"
  },
  "digit_results": {
    "T1": {
      "digit": "6",
      "score": 26134822.0,
      "confidence": null,
      "engine_used": "template_after_low_keras_confidence",
      "keras_confidence": 0.11359899491071701
    },
    "T2": {
      "digit": "2",
      "score": 24519645.0,
      "confidence": null,
      "engine_used": "template_after_low_keras_confidence",
      "keras_confidence": 0.11063702404499054
    },
    "T3": {
      "digit": "0",
      "score": 16119792.0,
      "confidence": null,
      "engine_used": "template_after_low_keras_confidence",
      "keras_confidence": 0.22096334397792816
    },
    "H1": {
      "digit": "5",
      "score": 21446600.0,
      "confidence": null,
      "engine_used": "template_after_low_keras_confidence",
      "keras_confidence": 0.13678382337093353
    },
    "H2": {
      "digit": "6",
      "score": 12404003.0,
      "confidence": null,
      "engine_used": "template_after_low_keras_confidence",
      "keras_confidence": 0.23094633221626282
    },
    "H3": {
      "digit": "2",
      "score": 13931864.0,
      "confidence": null,
      "engine_used": "template_after_low_keras_confidence",
      "keras_confidence": 0.2225816398859024
    }
  },
  "scores": {
    "T1": 26134822.0,
    "T2": 24519645.0,
    "T3": 16119792.0,
    "H1": 21446600.0,
    "H2": 12404003.0,
    "H3": 13931864.0
  },
  "engine_requested": "keras_then_template",
  "engine_used": "template_after_low_keras_confidence",
  "keras_confidence": null,
  "rotation": "180",
  "rotation_degrees": -7.0,
  "main_crop": {
    "x": 290,
    "y": 370,
    "w": 200,
    "h": 300
  },
  "digit_box_size": {
    "w": 450,
    "h": 800
  }
}